gistools/__init__.py
gistools/data_io.py
gistools/network.py
gistools/osm.py
gistools/raster.py
gistools/rec.py
gistools/util.py
gistools/vector.py
gistools/datasets/__init__.py
gistools-1.2.28.dist-info/LICENSE.txt
gistools-1.2.28.dist-info/METADATA
gistools-1.2.28.dist-info/WHEEL
gistools-1.2.28.dist-info/top_level.txt
gistools-1.2.28.dist-info/RECORD
