Metadata-Version: 2.1
Name: gistools
Version: 1.2.28
Summary: Misc geospatial functions built upon geopandas
Home-page: https://github.com/mullenkamp/gistools
Author: Mike Kittridge
Author-email: mullenkamp1@gmail.com
License: Apache
Keywords: gis geospatial
Classifier: Development Status :: 3 - Alpha
Classifier: Intended Audience :: Developers
Classifier: Topic :: Software Development :: Build Tools
Classifier: License :: OSI Approved :: Apache Software License
Classifier: Programming Language :: Python :: 2
Classifier: Programming Language :: Python :: 2.7
Classifier: Programming Language :: Python :: 3
Classifier: Programming Language :: Python :: 3.4
Classifier: Programming Language :: Python :: 3.5
Classifier: Programming Language :: Python :: 3.6
License-File: LICENSE.txt
Requires-Dist: geopandas
Requires-Dist: pycrs
Requires-Dist: scipy
Requires-Dist: overpass
Requires-Dist: osm2geojson
Requires-Dist: requests
Requires-Dist: orjson
Requires-Dist: rtree
